nanoleafapi-stubs/METADATA.toml
nanoleafapi-stubs/__init__.pyi
nanoleafapi-stubs/digital_twin.pyi
nanoleafapi-stubs/discovery.pyi
nanoleafapi-stubs/nanoleaf.pyi
nanoleafapi-stubs/py.typed
types_nanoleafapi-2.1.0.20241229.dist-info/LICENSE
types_nanoleafapi-2.1.0.20241229.dist-info/METADATA
types_nanoleafapi-2.1.0.20241229.dist-info/WHEEL
types_nanoleafapi-2.1.0.20241229.dist-info/top_level.txt
types_nanoleafapi-2.1.0.20241229.dist-info/RECORD
